transmutation/__init__.py
transmutation/alter.py
transmutation/alteration.py
transmutation/column.py
transmutation/constraint.py
transmutation/exceptions.py
transmutation/index.py
transmutation/migration.py
transmutation/py.typed
transmutation/table.py
transmutation/update.py
transmutation/utils.py
transmutation-1.3.0.dist-info/LICENSE
transmutation-1.3.0.dist-info/METADATA
transmutation-1.3.0.dist-info/WHEEL
transmutation-1.3.0.dist-info/top_level.txt
transmutation-1.3.0.dist-info/RECORD
