Metadata-Version: 2.1
Name: transmutation
Version: 1.3.0
Summary: Comprehensive database migration and schema alteration tool using SQLAlchemy and Alembic
Author: Odos Matthews
License: MIT
Project-URL: Homepage, https://github.com/odosmatthews/transmutation
Project-URL: Repository, https://github.com/odosmatthews/transmutation
Keywords: database,migration,schema,alembic,sqlalchemy
Classifier: Development Status :: 5 - Production/Stable
Classifier: Intended Audience :: Developers
Classifier: License :: OSI Approved :: MIT License
Classifier: Programming Language :: Python :: 3
Classifier: Programming Language :: Python :: 3.8
Classifier: Programming Language :: Python :: 3.9
Classifier: Programming Language :: Python :: 3.10
Classifier: Programming Language :: Python :: 3.11
Classifier: Programming Language :: Python :: 3.12
Classifier: Topic :: Database
Classifier: Topic :: Software Development :: Libraries :: Python Modules
Requires-Python: >=3.8
License-File: LICENSE
Requires-Dist: fullmetalalchemy>=2.4.0
Requires-Dist: alembic>=1.7.5
Requires-Dist: sqlalchemy<3.0,>=1.4.0
Provides-Extra: dev
Requires-Dist: pytest>=7.0.0; extra == "dev"
Requires-Dist: pytest-cov>=3.0.0; extra == "dev"
Requires-Dist: mypy>=0.990; extra == "dev"
Requires-Dist: ty>=0.0.1a25; extra == "dev"
Requires-Dist: flake8>=5.0.0; extra == "dev"
Requires-Dist: black>=22.0.0; extra == "dev"
Requires-Dist: isort>=5.10.0; extra == "dev"
Requires-Dist: tox>=4.0.0; extra == "dev"
Requires-Dist: testing.postgresql>=1.3.0; extra == "dev"
Requires-Dist: testing.mysqld>=1.4.0; extra == "dev"
Requires-Dist: psycopg2-binary>=2.9; extra == "dev"
Requires-Dist: pymysql>=1.0; extra == "dev"
